{
  "value": {
    "('Variables and Operations', 'prior', 'default')": 0.1157925635,
    "('Variables and Operations', 'learns', 'default')": 0.1491700996,
    "('Variables and Operations', 'guesses', 'default')": 0.0871180595,
    "('Variables and Operations', 'slips', 'default')": 0.2259290991,
    "('Variables and Operations', 'forgets', 'default')": 0.937432766,
    "('Boolean Expressions', 'prior', 'default')": 0.2982654947,
    "('Boolean Expressions', 'learns', 'default')": 0.1752868087,
    "('Boolean Expressions', 'guesses', 'default')": 0.252995469,
    "('Boolean Expressions', 'slips', 'default')": 0.0583574565,
    "('Boolean Expressions', 'forgets', 'default')": 0.4639269427,
    "('Strings', 'prior', 'default')": 0.0856851933,
    "('Strings', 'learns', 'default')": 0.0300899504,
    "('Strings', 'guesses', 'default')": 0.2365933209,
    "('Strings', 'slips', 'default')": 0.1547470528,
    "('Strings', 'forgets', 'default')": 0.5753551104,
    "('If-Else', 'prior', 'default')": 0.3934755512,
    "('If-Else', 'learns', 'default')": 0.111091838,
    "('If-Else', 'guesses', 'default')": 0.2650334463,
    "('If-Else', 'slips', 'default')": 0.0102016941,
    "('If-Else', 'forgets', 'default')": 0.9064590698,
    "('While Loops', 'prior', 'default')": 0.0702884711,
    "('While Loops', 'learns', 'default')": 0.0001691861,
    "('While Loops', 'guesses', 'default')": 0.165130736,
    "('While Loops', 'slips', 'default')": 0.2546982522,
    "('While Loops', 'forgets', 'default')": 0.0002724628,
    "('For Loops', 'prior', 'default')": 0.7205718905,
    "('For Loops', 'learns', 'default')": 0.0526456923,
    "('For Loops', 'guesses', 'default')": 0.3298610041,
    "('For Loops', 'slips', 'default')": 0.002633792,
    "('For Loops', 'forgets', 'default')": 0.6162868084,
    "('Objects and Classes', 'prior', 'default')": 0.1293587241,
    "('Objects and Classes', 'learns', 'default')": 0.6895984911,
    "('Objects and Classes', 'guesses', 'default')": 0.0000000653,
    "('Objects and Classes', 'slips', 'default')": 0.6349622038,
    "('Objects and Classes', 'forgets', 'default')": 0.9999928179,
    "('Nested Loops', 'prior', 'default')": 0.4438964052,
    "('Nested Loops', 'learns', 'default')": 0.1469404621,
    "('Nested Loops', 'guesses', 'default')": 0.0004743281,
    "('Nested Loops', 'slips', 'default')": 0.0631584803,
    "('Nested Loops', 'forgets', 'default')": 0.5747262263,
    "('Inheritance', 'prior', 'default')": 0.185708575,
    "('Inheritance', 'learns', 'default')": 0.149532732,
    "('Inheritance', 'guesses', 'default')": 0.0000048026,
    "('Inheritance', 'slips', 'default')": 0.3399533695,
    "('Inheritance', 'forgets', 'default')": 0.0274123401,
    "('ArrayLists', 'prior', 'default')": 0.0893162864,
    "('ArrayLists', 'learns', 'default')": 0.3344859946,
    "('ArrayLists', 'guesses', 'default')": 0.044807545,
    "('ArrayLists', 'slips', 'default')": 0.0573443888,
    "('ArrayLists', 'forgets', 'default')": 0.9436701101,
    "('Arrays', 'prior', 'default')": 0.5489600555,
    "('Arrays', 'learns', 'default')": 0.0005689293,
    "('Arrays', 'guesses', 'default')": 0.0522354649,
    "('Arrays', 'slips', 'default')": 0.2749496884,
    "('Arrays', 'forgets', 'default')": 0.0849855467,
    "('Two-Dimensional Arrays', 'prior', 'default')": 0.3063153167,
    "('Two-Dimensional Arrays', 'learns', 'default')": 0.0006350545,
    "('Two-Dimensional Arrays', 'guesses', 'default')": 0.1728078917,
    "('Two-Dimensional Arrays', 'slips', 'default')": 0.118807289,
    "('Two-Dimensional Arrays', 'forgets', 'default')": 0.4627755442,
    "('Exception handling', 'prior', 'default')": 0.7989767904,
    "('Exception handling', 'learns', 'default')": 0.0920408401,
    "('Exception handling', 'guesses', 'default')": 0.0,
    "('Exception handling', 'slips', 'default')": 0.6629276562,
    "('Exception handling', 'forgets', 'default')": 0.9996337108,
    "('File processing', 'prior', 'default')": 0.2084112538,
    "('File processing', 'learns', 'default')": 0.4579872909,
    "('File processing', 'guesses', 'default')": 0.0940362461,
    "('File processing', 'slips', 'default')": 0.3574843694,
    "('File processing', 'forgets', 'default')": 0.1508200577
  }
}
